hohmannpy/__init__.py
hohmannpy/astro/__init__.py
hohmannpy/astro/conversions.py
hohmannpy/astro/logging.py
hohmannpy/astro/mission.py
hohmannpy/astro/orbit.py
hohmannpy/astro/perturbations.py
hohmannpy/astro/time.py
hohmannpy/astro/propagation/__init__.py
hohmannpy/astro/propagation/base.py
hohmannpy/astro/propagation/cowell.py
hohmannpy/astro/propagation/encke.py
hohmannpy/astro/propagation/kepler.py
hohmannpy/astro/propagation/universal_variable.py
hohmannpy/dynamics/__init__.py
hohmannpy/dynamics/dcms.py
hohmannpy/resources/__init__.py
hohmannpy/ui/__init__.py
hohmannpy/ui/camera.py
hohmannpy/ui/rendering.py
hohmannpy-0.0.3.dist-info/licenses/LICENSE
hohmannpy-0.0.3.dist-info/METADATA
hohmannpy-0.0.3.dist-info/WHEEL
hohmannpy-0.0.3.dist-info/top_level.txt
hohmannpy-0.0.3.dist-info/RECORD
