Metadata-Version: 2.4
Name: hohmannpy
Version: 0.0.3
Summary: An open-source library designed for rapid spacecraft design and iteration.
Author: Nicholas Hirsch
License: GPL-3.0
Requires-Python: >=3.10
License-File: LICENSE
Requires-Dist: numpy
Requires-Dist: scipy
Requires-Dist: pygfx
Requires-Dist: pandas
Requires-Dist: imageio
Requires-Dist: pylinalg
Dynamic: license-file
